iexparsing/__init__.py
iexparsing/iextp.py
iexparsing/tops.py
iexparsing-0.2.1.dist-info/LICENSE
iexparsing-0.2.1.dist-info/WHEEL
iexparsing-0.2.1.dist-info/METADATA
iexparsing-0.2.1.dist-info/RECORD
