Metadata-Version: 2.1
Name: iexparsing
Version: 0.2.1
Summary: Parse IEX market data streams
Home-page: https://github.com/mmatamm/iexparsing
License: BSD-2-Clause
Keywords: IEX
Author: Amit Goren
Requires-Python: >=3.10,<4.0
Classifier: License :: OSI Approved :: BSD License
Classifier: Programming Language :: Python :: 3
Classifier: Programming Language :: Python :: 3.10
Requires-Dist: deprecation (>=2.1.0,<3.0.0)
Project-URL: Repository, https://github.com/mmatamm/iexparsing.git
